MANIFEST.in
README.md
pyproject.toml
setup.py
amuse_athena.egg-info/PKG-INFO
amuse_athena.egg-info/SOURCES.txt
amuse_athena.egg-info/dependency_links.txt
amuse_athena.egg-info/requires.txt
amuse_athena.egg-info/top_level.txt
src/amuse/community/athena/Makefile
src/amuse/community/athena/__init__.py
src/amuse/community/athena/_version.py
src/amuse/community/athena/amuse_problem_3.1.c
src/amuse/community/athena/amuse_problem_4.0.c
src/amuse/community/athena/amuse_problem_4.1.c
src/amuse/community/athena/download.py
src/amuse/community/athena/interface.py
src/amuse/community/athena/interface_3.1.c
src/amuse/community/athena/interface_4.0.c
src/amuse/community/athena/interface_4.1.c
src/amuse/community/athena/makefile.patch
src/amuse/community/athena/patch_files.py
src/amuse/community/athena/src/athena/Makefile.in
src/amuse/community/athena/src/athena/Makeoptions.in
src/amuse/community/athena/src/athena/configure
src/amuse/community/athena/src/athena/configure.ac
src/amuse/community/athena/src/athena/install-sh
src/amuse/community/athena/src/athena/autom4te.cache/output.0
src/amuse/community/athena/src/athena/autom4te.cache/requests
src/amuse/community/athena/src/athena/autom4te.cache/traces.0
src/amuse/community/athena/src/athena/doc/pbs-script
src/amuse/community/athena/src/athena/src/Makefile.in
src/amuse/community/athena/src/athena/src/ath_array.c
src/amuse/community/athena/src/athena/src/ath_files.c
src/amuse/community/athena/src/athena/src/ath_log.c
src/amuse/community/athena/src/athena/src/ath_signal.c
src/amuse/community/athena/src/athena/src/athena.h
src/amuse/community/athena/src/athena/src/baton.c
src/amuse/community/athena/src/athena/src/bvals_mhd.c
src/amuse/community/athena/src/athena/src/bvals_shear.c
src/amuse/community/athena/src/athena/src/cc_pos.c
src/amuse/community/athena/src/athena/src/config.h.in
src/amuse/community/athena/src/athena/src/convert_var.c
src/amuse/community/athena/src/athena/src/copyright.h
src/amuse/community/athena/src/athena/src/defs.h.in
src/amuse/community/athena/src/athena/src/dump_binary.c
src/amuse/community/athena/src/athena/src/dump_history.c
src/amuse/community/athena/src/athena/src/dump_tab.c
